kolors/__init__.py
kolors/models/__init__.py
kolors/models/configuration_chatglm.py
kolors/models/controlnet.py
kolors/models/modeling_chatglm.py
kolors/models/tokenization_chatglm.py
kolors/models/unet_2d_condition.py
kolors/models/ipa_faceid_plus/__init__.py
kolors/models/ipa_faceid_plus/attention_processor.py
kolors/models/ipa_faceid_plus/ipa_faceid_plus.py
kolors/pipelines/__init__.py
kolors/pipelines/pipeline_controlnet_xl_kolors_img2img.py
kolors/pipelines/pipeline_stable_diffusion_xl_chatglm_256.py
kolors/pipelines/pipeline_stable_diffusion_xl_chatglm_256_inpainting.py
kolors/pipelines/pipeline_stable_diffusion_xl_chatglm_256_ipadapter.py
kolors/pipelines/pipeline_stable_diffusion_xl_chatglm_256_ipadapter_FaceID.py
kolors_sdxl-0.0.2.dist-info/LICENSE
kolors_sdxl-0.0.2.dist-info/METADATA
kolors_sdxl-0.0.2.dist-info/WHEEL
kolors_sdxl-0.0.2.dist-info/top_level.txt
kolors_sdxl-0.0.2.dist-info/RECORD
